revolve2/experimentation/__init__.py
revolve2/experimentation/_util/__init__.py
revolve2/experimentation/_util/init_subclass_get_generic_args.py
revolve2/experimentation/database/__init__.py
revolve2/experimentation/database/_has_id.py
revolve2/experimentation/database/_open_method.py
revolve2/experimentation/database/_sqlite.py
revolve2/experimentation/evolution/__init__.py
revolve2/experimentation/evolution/_modular_robot_evolution.py
revolve2/experimentation/evolution/abstract_elements/__init__.py
revolve2/experimentation/evolution/abstract_elements/_evaluator.py
revolve2/experimentation/evolution/abstract_elements/_evolution.py
revolve2/experimentation/evolution/abstract_elements/_learner.py
revolve2/experimentation/evolution/abstract_elements/_reproducer.py
revolve2/experimentation/evolution/abstract_elements/_selector.py
revolve2/experimentation/logging.py
revolve2/experimentation/optimization/__init__.py
revolve2/experimentation/optimization/ea/__init__.py
revolve2/experimentation/optimization/ea/_generation.py
revolve2/experimentation/optimization/ea/_individual.py
revolve2/experimentation/optimization/ea/_parameters.py
revolve2/experimentation/optimization/ea/_population.py
revolve2/experimentation/optimization/ea/population_management/__init__.py
revolve2/experimentation/optimization/ea/population_management/_generational.py
revolve2/experimentation/optimization/ea/population_management/_steady_state.py
revolve2/experimentation/optimization/ea/selection/__init__.py
revolve2/experimentation/optimization/ea/selection/_argsort.py
revolve2/experimentation/optimization/ea/selection/_multiple_unique.py
revolve2/experimentation/optimization/ea/selection/_pareto_frontier.py
revolve2/experimentation/optimization/ea/selection/_supports_lt.py
revolve2/experimentation/optimization/ea/selection/_topn.py
revolve2/experimentation/optimization/ea/selection/_tournament.py
revolve2/experimentation/py.typed
revolve2/experimentation/rng.py
revolve2_experimentation-1.2.4.dist-info/METADATA
revolve2_experimentation-1.2.4.dist-info/WHEEL
revolve2_experimentation-1.2.4.dist-info/RECORD
