Metadata-Version: 2.3
Name: revolve2-experimentation
Version: 1.2.4
Summary: Revolve2: Tools for experimentation.
Author: Aart Stuurman
Author-email: aartstuurman@hotmail.com
Requires-Python: >=3.10,<3.12
Classifier: Development Status :: 5 - Production/Stable
Classifier: Intended Audience :: Science/Research
Classifier: License :: OSI Approved :: GNU Lesser General Public License v3 (LGPLv3)
Classifier: Operating System :: OS Independent
Classifier: Programming Language :: Python :: 3
Classifier: Programming Language :: Python :: 3.10
Classifier: Programming Language :: Python :: 3.11
Classifier: Topic :: Scientific/Engineering
Classifier: Typing :: Typed
Provides-Extra: dev
Requires-Dist: numpy (>=1.21.2,<2.0.0)
Requires-Dist: sqlalchemy (>=2.0.0,<3.0.0)
Project-URL: Repository, https://github.com/ci-group/revolve2
